[
  {
    "_id": "xP90m",
    "title": "ssss",
    "description": "s",
    "severity": 3,
    "createdAt": 1668616292717,
    "owner": {
      "_id": "Vv58l",
      "fullname": "Guli Yat"
    }
  },
  
  {
    "_id": "yR8S3",
    "title": "jhijhi",
    "description": "jhjh",
    "severity": 2,
    "createdAt": 1668599340432,
    "owner": {
      "_id": "zQuW7",
      "fullname": "Puki Ga"
    }
  },
  {
    "_id": "ppqRC",
    "title": "test",
    "description": "desc test",
    "severity": 3,
    "createdAt": 1668602560999,
    "owner": {
      "_id": "iFeco",
      "fullname": "Muki Ba"
    }
  },
  {
    "_id": "cvkSD",
    "title": "test",
    "description": "desc test",
    "severity": 5,
    "createdAt": "1694859356"
  }

]